c7n_left/cli.py
c7n_left/core.py
c7n_left/entry.py
c7n_left/filters.py
c7n_left/output.py
c7n_left/policy.py
c7n_left/test.py
c7n_left/utils.py
c7n_left/validate.py
c7n_left/data/taggable.json
c7n_left/providers/terraform/__init__.py
c7n_left/providers/terraform/filters.py
c7n_left/providers/terraform/graph.py
c7n_left/providers/terraform/provider.py
c7n_left/providers/terraform/resource.py
c7n_left/providers/terraform/variables.py
c7n_left-0.3.35.dist-info/METADATA
c7n_left-0.3.35.dist-info/WHEEL
c7n_left-0.3.35.dist-info/entry_points.txt
c7n_left-0.3.35.dist-info/RECORD
