Metadata-Version: 2.4
Name: c7n_left
Version: 0.3.35
Summary: Custodian policies for IAAC definitions
Project-URL: homepage, https://cloudcustodian.io
Project-URL: repository, https://github.com/cloud-custodian/cloud-custodian
Project-URL: documentation, https://cloudcustodian.io/docs/
Author: Cloud Custodian Project
License: Apache-2
Classifier: License :: OSI Approved :: Apache Software License
Classifier: Topic :: System :: Distributed Computing
Classifier: Topic :: System :: Systems Administration
Requires-Python: <4.0.0,>=3.9.2
Requires-Dist: c7n ==0.9.49
Requires-Dist: click ==8.3.1
Requires-Dist: python-hcl2 ==4.3.5
Requires-Dist: rich ==14.2.0
Requires-Dist: tfparse ==0.6.19
